mill_cache/__init__.py
mill_cache/main.py
mill_cache/version.py
mill_cache/assets/cache.tar.gz
mill_cache-0.3.1.dist-info/METADATA
mill_cache-0.3.1.dist-info/WHEEL
mill_cache-0.3.1.dist-info/entry_points.txt
mill_cache-0.3.1.dist-info/top_level.txt
mill_cache-0.3.1.dist-info/RECORD
